my-project/verilog_programming/parametric_counter/parametric_counter.sv
module parametric_counter #(parameter int width = 4) (
    input logic reset , up,down,clock,
    input logic [width-1:0]initial_value,
    output logic [width-1:0]count=0
);

    always_ff @( clock ) begin 
        if (reset) begin
            count<=initial_value;
        end
        else if (up) begin
            count<=count+1'b1;
        end
        else if (down)begin
            count <=count - 1'b1;
        end
    end
endmodule

my-project/verilog_programming/parametric_counter/parametric_counter_tb.sv
module parametric_counter_tb #(parameter width=4)();
    logic up,down,reset,clock;
    logic [width-1:0]initial_value,count;
    parametric_counter uut1(.up(up),.down(down),.reset(reset),.clock(clock),.initial_value(initial_value),.count(count));
    always #0.5 clock=~clock ; 
    initial begin
        clock=0;
        up=0;
        down=0;
        reset=0;
        initial_value=3'd7;
        #2;
        for (int i=0 ;i<=16;i++) begin
        up=$random;
        #2;
        down=$random;
        #2;
        reset=$random;
        #2;
        initial_value=$random;
        #2;
        end
        $finish;
       end
    initial begin
        $dumpfile("parameteric_counter.vcd");
        $dumpvars(0,parametric_counter_tb);
    end
endmodule

my-project/verilog_programming/parametric_counter/parameteric_counter.vcd
$date
	Mon Jul  8 17:00:59 2024
$end
$version
	ModelSim Version 2020.1
$end
$timescale
	1ps
$end

$scope module parametric_counter_tb $end
$var parameter 32 ! width $end
$var reg 1 " up $end
$var reg 1 # down $end
$var reg 1 $ reset $end
$var reg 1 % clock $end
$var reg 4 & initial_value [3:0] $end
$var reg 4 ' count [3:0] $end

$scope module uut1 $end
$var parameter 32 ( width $end
$var wire 1 ) reset $end
$var wire 1 * up $end
$var wire 1 + down $end
$var wire 1 , clock $end
$var wire 1 - initial_value [3] $end
$var wire 1 . initial_value [2] $end
$var wire 1 / initial_value [1] $end
$var wire 1 0 initial_value [0] $end
$var reg 4 1 count [3:0] $end
$upscope $end
$upscope $end
$enddefinitions $end
#0
$dumpvars
0"
0#
0$
0%
b111 &
b0 '
b0 1
b100 !
b100 (
0*
0+
0)
0,
10
1/
1.
0-
$end
#1
1%
1,
#2
0%
0,
#3
1%
1,
#4
1#
0%
1+
0,
b1111 1
b1111 '
#5
1%
1,
b1110 1
b1110 '
#6
1$
0%
1)
0,
b111 1
b111 '
#7
1%
1,
#8
b11 &
0%
0.
0,
b11 1
b11 '
#9
1%
1,
#10
1"
0%
1*
0,
#11
1%
1,
#12
0%
0,
#13
1%
1,
#14
0%
0,
#15
1%
1,
#16
b10 &
0%
00
0,
b10 1
b10 '
#17
1%
1,
#18
0%
0,
#19
1%
1,
#20
0%
0,
#21
1%
1,
#22
0$
0%
0)
0,
b11 1
b11 '
#23
1%
1,
b100 1
b100 '
#24
b1101 &
0%
10
0/
1.
1-
0,
b101 1
b101 '
#25
1%
1,
b110 1
b110 '
#26
0%
0,
b111 1
b111 '
#27
1%
1,
b1000 1
b1000 '
#28
0#
0%
0+
0,
b1001 1
b1001 '
#29
1%
1,
b1010 1
b1010 '
#30
1$
0%
1)
0,
b1101 1
b1101 '
#31
1%
1,
#32
b110 &
0%
00
1/
0-
0,
b110 1
b110 '
#33
1%
1,
#34
0%
0,
#35
1%
1,
#36
0%
0,
#37
1%
1,
#38
0%
0,
#39
1%
1,
#40
b111 &
0%
10
0,
b111 1
b111 '
#41
1%
1,
#42
0"
0%
0*
0,
#43
1%
1,
#44
1#
0%
1+
0,
#45
1%
1,
#46
0$
0%
0)
0,
b110 1
b110 '
#47
1%
1,
b101 1
b101 '
#48
b1110 &
0%
00
1-
0,
b100 1
b100 '
#49
1%
1,
b11 1
b11 '
#50
0%
0,
b10 1
b10 '
#51
1%
1,
b1 1
b1 '
#52
0%
0,
b0 1
b0 '
#53
1%
1,
b1111 1
b1111 '
#54
0%
0,
b1110 1
b1110 '
#55
1%
1,
b1101 1
b1101 '
#56
b1101 &
0%
10
0/
0,
b1100 1
b1100 '
#57
1%
1,
b1011 1
b1011 '
#58
1"
0%
1*
0,
b1100 1
b1100 '
#59
1%
1,
b1101 1
b1101 '
#60
0%
0,
b1110 1
b1110 '
#61
1%
1,
b1111 1
b1111 '
#62
1$
0%
1)
0,
b1101 1
b1101 '
#63
1%
1,
#64
b1010 &
0%
00
1/
0.
0,
b1010 1
b1010 '
#65
1%
1,
#66
0"
0%
0*
0,
#67
1%
1,
#68
0#
0%
0+
0,
#69
1%
1,
#70
0$
0%
0)
0,
#71
1%
1,
#72
b1101 &
0%
10
0/
1.
0,
#73
1%
1,
#74
0%
0,
#75
1%
1,
#76
1#
0%
1+
0,
b1001 1
b1001 '
#77
1%
1,
b1000 1
b1000 '
#78
1$
0%
1)
0,
b1101 1
b1101 '
#79
1%
1,
#80
b11 &
0%
1/
0.
0-
0,
b11 1
b11 '
#81
1%
1,
#82
1"
0%
1*
0,
#83
1%
1,
#84
0%
0,
#85
1%
1,
#86
0$
0%
0)
0,
b100 1
b100 '
#87
1%
1,
b101 1
b101 '
#88
b1110 &
0%
00
1.
1-
0,
b110 1
b110 '
#89
1%
1,
b111 1
b111 '
#90
0%
0,
b1000 1
b1000 '
#91
1%
1,
b1001 1
b1001 '
#92
0%
0,
b1010 1
b1010 '
#93
1%
1,
b1011 1
b1011 '
#94
1$
0%
1)
0,
b1110 1
b1110 '
#95
1%
1,
#96
b1010 &
0%
0.
0,
b1010 1
b1010 '
#97
1%
1,
#98
0"
0%
0*
0,
#99
1%
1,
#100
0#
0%
0+
0,
#101
1%
1,
#102
0$
0%
0)
0,
#103
1%
1,
#104
0%
0,
#105
1%
1,
#106
1"
0%
1*
0,
b1011 1
b1011 '
#107
1%
1,
b1100 1
b1100 '
#108
0%
0,
b1101 1
b1101 '
#109
1%
1,
b1110 1
b1110 '
#110
0%
0,
b1111 1
b1111 '
#111
1%
1,
b0 1
b0 '
#112
b1001 &
0%
10
0/
0,
b1 1
b1 '
#113
1%
1,
b10 1
b10 '
#114
0%
0,
b11 1
b11 '
#115
1%
1,
b100 1
b100 '
#116
0%
0,
b101 1
b101 '
#117
1%
1,
b110 1
b110 '
#118
0%
0,
b111 1
b111 '
#119
1%
1,
b1000 1
b1000 '
#120
b1110 &
0%
00
1/
1.
0,
b1001 1
b1001 '
#121
1%
1,
b1010 1
b1010 '
#122
0"
0%
0*
0,
#123
1%
1,
#124
0%
0,
#125
1%
1,
#126
1$
0%
1)
0,
b1110 1
b1110 '
#127
1%
1,
#128
b1 &
0%
10
0/
0.
0-
0,
b1 1
b1 '
#129
1%
1,
#130
1"
0%
1*
0,
#131
1%
1,
#132
1#
0%
1+
0,
#133
1%
1,
#134
0%
0,
#135
1%
1,
#136
b1010 &
0%
00
1/
1-
0,
b1010 1
b1010 '
