my-project/verilog_programming/seven_segment_display/SSD.v
module SSD(
    input [3:0]no,
    output reg [6:0]segments
);
always @(*) begin
    case (no)
    4'h0:segments=7'b0000001;
    4'h1:segments=7'b1001111;
    4'h2:segments=7'b0010010;
    4'h3:segments=7'b0000110;
    4'h4:segments=7'b1001100;
    4'h5:segments=7'b0100100;
    4'h6:segments=7'b0100000;
    4'h7:segments=7'b0001111;
    4'h8:segments=7'b0000000;
    4'h9:segments=7'b0000100;
    4'hA:segments=7'b0001000;
    4'hB:segments=7'b1100000;
    4'hC:segments=7'b0110001;
    4'hD:segments=7'b1000010;
    4'hE:segments=7'b0110000;
    4'hF:segments=7'b0111000; 
        default: 
        segments=7'b1111111;
    endcase
end
endmodule

my-project/verilog_programming/seven_segment_display/SSD_tb.v
module SSD_tb ();
    wire[6:0]segments;
    reg [3:0]no;
    reg [6:0]expected_value_segments[15:0];
    integer i;
SSD uut(.segments(segments),.no(no)); 
initial begin
expected_value_segments[0]=7'b0000001;
expected_value_segments[1]=7'b1001111;
expected_value_segments[2]=7'b0010010;
expected_value_segments[3]=7'b0000110;
expected_value_segments[4]=7'b1001100;
expected_value_segments[5]=7'b0100100;
expected_value_segments[6]=7'b0100000;
expected_value_segments[7]=7'b0001111;
expected_value_segments[8]=7'b0000000;
expected_value_segments[9]=7'b0000100;
expected_value_segments[10]=7'b0001000;
expected_value_segments[11]=7'b1100000;
expected_value_segments[12]=7'b0110001;
expected_value_segments[13]=7'b1000010;
expected_value_segments[14]=7'b0110000;
expected_value_segments[15]=7'b0111000;
    $dumpfile("SSD.vcd");
    $dumpvars(0,SSD_tb);
    for (i=0;i<=15;i++) begin 
         no=i;
         #1;
        if (segments == expected_value_segments[i]) begin
            $display("%h     matched",no);
        end
        else begin
           $display("%h    not matched",no); 

        end

    end 
end

endmodule

my-project/verilog_programming/seven_segment_display/SSD.vcd
$date
	Mon Jul  1 17:56:57 2024
$end
$version
	Icarus Verilog
$end
$timescale
	1s
$end
$scope module SSD_tb $end
$var wire 7 ! segments [6:0] $end
$var reg 4 " no [3:0] $end
$var integer 32 # i [31:0] $end
$scope module uut $end
$var wire 4 $ no [3:0] $end
$var reg 7 % segments [6:0] $end
$upscope $end
$upscope $end
$enddefinitions $end
$comment Show the parameter values. $end
$dumpall
$end
#0
$dumpvars
b1 %
b0 $
b0 #
b0 "
b1 !
$end
#1
b1001111 !
b1001111 %
b1 "
b1 $
b1 #
#2
b10010 !
b10010 %
b10 "
b10 $
b10 #
#3
b110 !
b110 %
b11 "
b11 $
b11 #
#4
b1001100 !
b1001100 %
b100 "
b100 $
b100 #
#5
b100100 !
b100100 %
b101 "
b101 $
b101 #
#6
b100000 !
b100000 %
b110 "
b110 $
b110 #
#7
b1111 !
b1111 %
b111 "
b111 $
b111 #
#8
b0 !
b0 %
b1000 "
b1000 $
b1000 #
#9
b100 !
b100 %
b1001 "
b1001 $
b1001 #
#10
b1000 !
b1000 %
b1010 "
b1010 $
b1010 #
#11
b1100000 !
b1100000 %
b1011 "
b1011 $
b1011 #
#12
b110001 !
b110001 %
b1100 "
b1100 $
b1100 #
#13
b1000010 !
b1000010 %
b1101 "
b1101 $
b1101 #
#14
b110000 !
b110000 %
b1110 "
b1110 $
b1110 #
#15
b111000 !
b111000 %
b1111 "
b1111 $
b1111 #
#16
b10000 #
