my-project/verilog_programming/FIFO_queue/fifo_queue.sv
module fifo_queue #(parameter depth = 3 ,parameter width =3)(input logic [width-1:0]q_in ,
input logic reset,clock,enqueue,dequeue,
output logic [width-1:0]q_out ,logic full,empty    
);
    logic [depth:0]count=0;
    logic [width-1:0]queue[depth-1:0]='{default:0};
    always_ff @( posedge clock ) begin 
        if (reset) begin
            count <=0;
            queue <= '{default:0};
        end
        else if (enqueue && !(count==depth)) begin
            queue[count]<=q_in;
            count <=count+1;
        end
        else if (dequeue && !(count==0)) begin
            for (int i =0 ;i<width-1 ;i++ ) begin
               queue[i]<=queue[i+1];
            end
            queue[width-1]=0;
            count<=count-1;
        end
    end
    always_comb begin
      if (count==depth) begin
        full=1'b1;
      end 
      else full=1'b0; 
    end
    always_comb begin
        if (count==0) begin
            empty=1'b1;
        end else begin
            empty=1'b0;
        end
    end
    always_comb begin 
        if (dequeue && !(count==0)) begin
            q_out=queue[0];
        end
        else begin
            q_out=0;
        end
    end
endmodule

my-project/verilog_programming/FIFO_queue/fifo_queue_tb.sv
module fifo_queue_tb#(parameter width =3) ();
    logic [width-1:0]q_in,q_out;
    logic clock,reset,enqueue,dequeue,empty,full;
    fifo_queue uut1(.q_in(q_in),.q_out(q_out),.reset(reset),.clock(clock),.empty(empty),.full(full),.enqueue(enqueue),.dequeue(dequeue));
    
    initial begin
        clock=0;
        q_in=1;
        reset=0;
        enqueue=1;
        dequeue=0;
        #5;
        for (int i=0;i<=15;i++) begin
        q_in=$random;
        #5;
        reset=$random;
        #5;
        enqueue=$random;
        #5;
        dequeue=$random;
        #5;   
        end
        $finish;
    end
    always #1 clock=~clock;
    initial begin
        $dumpfile("fifo_queue.vcd");
        $dumpvars(0,fifo_queue_tb);
    end
endmodule

my-project/verilog_programming/FIFO_queue/fifo_queue.vcd
$date
	Tue Jul  9 11:00:36 2024
$end
$version
	ModelSim Version 2020.1
$end
$timescale
	1ps
$end

$scope module fifo_queue_tb $end
$var parameter 32 ! width $end
$var reg 3 " q_in [2:0] $end
$var reg 3 # q_out [2:0] $end
$var reg 1 $ clock $end
$var reg 1 % reset $end
$var reg 1 & enqueue $end
$var reg 1 ' dequeue $end
$var reg 1 ( empty $end
$var reg 1 ) full $end

$scope module uut1 $end
$var parameter 32 * depth $end
$var parameter 32 + width $end
$var wire 1 , q_in [2] $end
$var wire 1 - q_in [1] $end
$var wire 1 . q_in [0] $end
$var wire 1 / reset $end
$var wire 1 0 clock $end
$var wire 1 1 enqueue $end
$var wire 1 2 dequeue $end
$var reg 3 3 q_out [2:0] $end
$var reg 1 4 full $end
$var reg 1 5 empty $end
$var reg 4 6 count [3:0] $end
$upscope $end
$upscope $end
$enddefinitions $end
#0
$dumpvars
b1 "
b0 #
0$
0%
1&
0'
1(
0)
b0 3
04
15
b0 6
b11 !
b11 *
b11 +
1.
0-
0,
0/
00
11
02
$end
#1
1$
10
b1 6
05
0(
#2
0$
00
#3
1$
10
b10 6
#4
0$
00
#5
b100 "
1$
0.
1,
10
b11 6
14
1)
#6
0$
00
#7
1$
10
#8
0$
00
#9
1$
10
#10
1%
0$
1/
00
#11
1$
10
b0 6
04
15
1(
0)
#12
0$
00
#13
1$
10
#14
0$
00
#15
1$
10
#16
0$
00
#17
1$
10
#18
0$
00
#19
1$
10
#20
1'
0$
12
00
#21
1$
10
#22
0$
00
#23
1$
10
#24
0$
00
#25
b101 "
1$
1.
10
#26
0$
00
#27
1$
10
#28
0$
00
#29
1$
10
#30
0$
00
#31
1$
10
#32
0$
00
#33
1$
10
#34
0$
00
#35
1$
10
#36
0$
00
#37
1$
10
#38
0$
00
#39
1$
10
#40
0'
0$
02
00
#41
1$
10
#42
0$
00
#43
1$
10
#44
0$
00
#45
b1 "
1$
0,
10
#46
0$
00
#47
1$
10
#48
0$
00
#49
1$
10
#50
0$
00
#51
1$
10
#52
0$
00
#53
1$
10
#54
0$
00
#55
0&
1$
01
10
#56
0$
00
#57
1$
10
#58
0$
00
#59
1$
10
#60
1'
0$
12
00
#61
1$
10
#62
0$
00
#63
1$
10
#64
0$
00
#65
b101 "
1$
1,
10
#66
0$
00
#67
1$
10
#68
0$
00
#69
1$
10
#70
0%
0$
0/
00
#71
1$
10
#72
0$
00
#73
1$
10
#74
0$
00
#75
1&
1$
11
10
b1 6
05
b101 3
b101 #
0(
#76
0$
00
#77
1$
10
b10 6
#78
0$
00
#79
1$
10
b11 6
14
1)
#80
0'
0$
02
00
b0 3
b0 #
#81
1$
10
#82
0$
00
#83
1$
10
#84
0$
00
#85
1$
10
#86
0$
00
#87
1$
10
#88
0$
00
#89
1$
10
#90
0$
00
#91
1$
10
#92
0$
00
#93
1$
10
#94
0$
00
#95
1$
10
#96
0$
00
#97
1$
10
#98
0$
00
#99
1$
10
#100
1'
0$
12
00
b101 3
b101 #
#101
1$
10
b10 6
04
0)
#102
0$
00
#103
1$
10
b11 6
14
1)
#104
0$
00
#105
b10 "
1$
0.
1-
0,
10
b10 6
04
0)
#106
0$
00
#107
1$
10
b11 6
14
1)
#108
0$
00
#109
1$
10
b10 6
04
0)
#110
1%
0$
1/
00
#111
1$
10
b0 6
15
b0 3
b0 #
1(
#112
0$
00
#113
1$
10
#114
0$
00
#115
0&
1$
01
10
#116
0$
00
#117
1$
10
#118
0$
00
#119
1$
10
#120
0'
0$
02
00
#121
1$
10
#122
0$
00
#123
1$
10
#124
0$
00
#125
b0 "
1$
0-
10
#126
0$
00
#127
1$
10
#128
0$
00
#129
1$
10
#130
0$
00
#131
1$
10
#132
0$
00
#133
1$
10
#134
0$
00
#135
1$
10
#136
0$
00
#137
1$
10
#138
0$
00
#139
1$
10
#140
1'
0$
12
00
#141
1$
10
#142
0$
00
#143
1$
10
#144
0$
00
#145
b101 "
1$
1.
1,
10
#146
0$
00
#147
1$
10
#148
0$
00
#149
1$
10
#150
0$
00
#151
1$
10
#152
0$
00
#153
1$
10
#154
0$
00
#155
1&
1$
11
10
#156
0$
00
#157
1$
10
#158
0$
00
#159
1$
10
#160
0'
0$
02
00
#161
1$
10
#162
0$
00
#163
1$
10
#164
0$
00
#165
b0 "
1$
0.
0,
10
#166
0$
00
#167
1$
10
#168
0$
00
#169
1$
10
#170
0%
0$
0/
00
#171
1$
10
b1 6
05
0(
#172
0$
00
#173
1$
10
b10 6
#174
0$
00
#175
0&
1$
01
10
#176
0$
00
#177
1$
10
#178
0$
00
#179
1$
10
#180
1'
0$
12
00
#181
1$
10
b1 6
#182
0$
00
#183
1$
10
b0 6
15
1(
#184
0$
00
#185
b110 "
1$
1-
1,
10
#186
0$
00
#187
1$
10
#188
0$
00
#189
1$
10
#190
1%
0$
1/
00
#191
1$
10
#192
0$
00
#193
1$
10
#194
0$
00
#195
1&
1$
11
10
#196
0$
00
#197
1$
10
#198
0$
00
#199
1$
10
#200
0$
00
#201
1$
10
#202
0$
00
#203
1$
10
#204
0$
00
#205
b11 "
1$
1.
0,
10
#206
0$
00
#207
1$
10
#208
0$
00
#209
1$
10
#210
0$
00
#211
1$
10
#212
0$
00
#213
1$
10
#214
0$
00
#215
0&
1$
01
10
#216
0$
00
#217
1$
10
#218
0$
00
#219
1$
10
#220
0'
0$
02
00
#221
1$
10
#222
0$
00
#223
1$
10
#224
0$
00
#225
b101 "
1$
0-
1,
10
#226
0$
00
#227
1$
10
#228
0$
00
#229
1$
10
#230
0$
00
#231
1$
10
#232
0$
00
#233
1$
10
#234
0$
00
#235
1&
1$
11
10
#236
0$
00
#237
1$
10
#238
0$
00
#239
1$
10
#240
0$
00
#241
1$
10
#242
0$
00
#243
1$
10
#244
0$
00
#245
b10 "
1$
0.
1-
0,
10
#246
0$
00
#247
1$
10
#248
0$
00
#249
1$
10
#250
0%
0$
0/
00
#251
1$
10
b1 6
05
0(
#252
0$
00
#253
1$
10
b10 6
#254
0$
00
#255
0&
1$
01
10
#256
0$
00
#257
1$
10
#258
0$
00
#259
1$
10
#260
0$
00
#261
1$
10
#262
0$
00
#263
1$
10
#264
0$
00
#265
b1 "
1$
1.
0-
10
#266
0$
00
#267
1$
10
#268
0$
00
#269
1$
10
#270
0$
00
#271
1$
10
#272
0$
00
#273
1$
10
#274
0$
00
#275
1$
10
#276
0$
00
#277
1$
10
#278
0$
00
#279
1$
10
#280
1'
0$
12
00
b10 3
b10 #
#281
1$
10
b1 6
#282
0$
00
#283
1$
10
b0 6
15
b0 3
b0 #
1(
#284
0$
00
#285
b11 "
1$
1-
10
#286
0$
00
#287
1$
10
#288
0$
00
#289
1$
10
#290
0$
00
#291
1$
10
#292
0$
00
#293
1$
10
#294
0$
00
#295
1$
10
#296
0$
00
#297
1$
10
#298
0$
00
#299
1$
10
#300
0'
0$
02
00
#301
1$
10
#302
0$
00
#303
1$
10
#304
0$
00
#305
b100 "
1$
0.
0-
1,
10
#306
0$
00
#307
1$
10
#308
0$
00
#309
1$
10
#310
0$
00
#311
1$
10
#312
0$
00
#313
1$
10
#314
0$
00
#315
1&
1$
11
10
b1 6
05
0(
#316
0$
00
#317
1$
10
b10 6
#318
0$
00
#319
1$
10
b11 6
14
1)
#320
1'
0$
12
00
b100 3
b100 #
#321
1$
10
b10 6
04
0)
#322
0$
00
#323
1$
10
b11 6
14
1)
