my-project/verilog_programming/adder_4bit/full_adder.v
module full_adder(input wire a,b,c,
	output wire sum,carry);
	       assign carry=(a&b) | (a&c) | (b&c);
	       assign sum=(a^b^c);
endmodule

my-project/verilog_programming/adder_4bit/adder_4bit.v
module adder_4bit( input wire [3:0]x,y, 
                   output wire [3:0]sum,
		           output wire carry);
 wire [3:0]c;
 assign c[0]=1'b0;
 full_adder uu1(.a(x[0]) ,.b(y[0]) ,.c(c[0]) ,.sum(sum[0]),.carry(c[1]));
 full_adder uu2(.a(x[1]) ,.b(y[1]) ,.c(c[1]) ,.sum(sum[1]),.carry(c[2])); 
 full_adder uu3(.a(x[2]) ,.b(y[2]) ,.c(c[2]) ,.sum(sum[2]),.carry(c[3]));
 full_adder uu4(.a(x[3]) ,.b(y[3]) ,.c(c[3]) ,.sum(sum[3]),.carry(carry)); 
endmodule

my-project/verilog_programming/adder_4bit/adder_4bit_tb.v
module adder_4bit_tb();
reg [3:0]x,y;
wire [3:0]sum;
wire carry;
integer i,j;
adder_4bit but(.x(x), .y(y), .sum(sum), .carry(carry));

initial begin
	$dumpfile("adder_4bit.vcd");
	$dumpvars(0,adder_4bit_tb);
	$monitor("%b + %b = %b%b",x,y,carry,sum);
	for (i=0;i<=15;i=i+1)begin
		x=i;
		for (j=0;j<=15;j=j+1)begin
			y=j;
			#1;
		end
	end
$stop;	 
end
endmodule

my-project/verilog_programming/adder_4bit/adder_4bit.vcd
$date
	Mon Jul  1 10:59:01 2024
$end
$version
	Icarus Verilog
$end
$timescale
	1s
$end
$scope module adder_4bit_tb $end
$var wire 4 ! sum [3:0] $end
$var wire 1 " carry $end
$var reg 4 # x [3:0] $end
$var reg 4 $ y [3:0] $end
$var integer 32 % i [31:0] $end
$var integer 32 & j [31:0] $end
$scope module but $end
$var wire 4 ' x [3:0] $end
$var wire 4 ( y [3:0] $end
$var wire 4 ) sum [3:0] $end
$var wire 1 " carry $end
$var wire 4 * c [3:0] $end
$scope module uu1 $end
$var wire 1 + a $end
$var wire 1 , b $end
$var wire 1 - c $end
$var wire 1 . carry $end
$var wire 1 / sum $end
$upscope $end
$scope module uu2 $end
$var wire 1 0 a $end
$var wire 1 1 b $end
$var wire 1 2 c $end
$var wire 1 3 carry $end
$var wire 1 4 sum $end
$upscope $end
$scope module uu3 $end
$var wire 1 5 a $end
$var wire 1 6 b $end
$var wire 1 7 c $end
$var wire 1 8 carry $end
$var wire 1 9 sum $end
$upscope $end
$scope module uu4 $end
$var wire 1 : a $end
$var wire 1 ; b $end
$var wire 1 < c $end
$var wire 1 " carry $end
$var wire 1 = sum $end
$upscope $end
$upscope $end
$upscope $end
$enddefinitions $end
$comment Show the parameter values. $end
$dumpall
$end
#0
$dumpvars
0=
0<
0;
0:
09
08
07
06
05
04
03
02
01
00
0/
0.
0-
0,
0+
b0 *
b0 )
b0 (
b0 '
b0 &
b0 %
b0 $
b0 #
0"
b0 !
$end
#1
b1 !
b1 )
1/
1,
b1 $
b1 (
b1 &
#2
0/
b10 !
b10 )
14
0,
11
b10 $
b10 (
b10 &
#3
b11 !
b11 )
1/
1,
b11 $
b11 (
b11 &
#4
0/
04
b100 !
b100 )
19
0,
01
16
b100 $
b100 (
b100 &
#5
b101 !
b101 )
1/
1,
b101 $
b101 (
b101 &
#6
0/
b110 !
b110 )
14
0,
11
b110 $
b110 (
b110 &
#7
b111 !
b111 )
1/
1,
b111 $
b111 (
b111 &
#8
0/
04
09
b1000 !
b1000 )
1=
0,
01
06
1;
b1000 $
b1000 (
b1000 &
#9
b1001 !
b1001 )
1/
1,
b1001 $
b1001 (
b1001 &
#10
0/
b1010 !
b1010 )
14
0,
11
b1010 $
b1010 (
b1010 &
#11
b1011 !
b1011 )
1/
1,
b1011 $
b1011 (
b1011 &
#12
0/
04
b1100 !
b1100 )
19
0,
01
16
b1100 $
b1100 (
b1100 &
#13
b1101 !
b1101 )
1/
1,
b1101 $
b1101 (
b1101 &
#14
0/
b1110 !
b1110 )
14
0,
11
b1110 $
b1110 (
b1110 &
#15
b1111 !
b1111 )
1/
1,
b1111 $
b1111 (
b1111 &
#16
04
09
b1 !
b1 )
0=
0,
01
06
0;
1+
b0 $
b0 (
b1 #
b1 '
b1 %
b0 &
#17
14
12
b10 *
1.
b10 !
b10 )
0/
1,
b1 $
b1 (
b1 &
#18
02
09
0.
07
1/
b0 *
03
b11 !
b11 )
14
0,
11
b10 $
b10 (
b10 &
#19
19
17
13
04
12
b110 *
1.
b100 !
b100 )
0/
1,
b11 $
b11 (
b11 &
#20
02
0=
0.
07
0<
1/
03
04
b0 *
08
b101 !
b101 )
19
0,
01
16
b100 $
b100 (
b100 &
#21
14
12
b10 *
1.
b110 !
b110 )
0/
1,
b101 $
b101 (
b101 &
#22
0=
0<
08
02
19
0.
07
1/
b0 *
03
b111 !
b111 )
14
0,
11
b110 $
b110 (
b110 &
#23
1=
1<
18
09
17
13
04
12
b1110 *
1.
b1000 !
b1000 )
0/
1,
b111 $
b111 (
b111 &
#24
02
0.
07
0<
1/
03
04
b0 *
08
09
0"
b1001 !
b1001 )
1=
0,
01
06
1;
b1000 $
b1000 (
b1000 &
#25
14
12
b10 *
1.
b1010 !
b1010 )
0/
1,
b1001 $
b1001 (
b1001 &
#26
02
09
0.
07
1/
b0 *
03
b1011 !
b1011 )
14
0,
11
b1010 $
b1010 (
b1010 &
#27
19
17
13
04
12
b110 *
1.
b1100 !
b1100 )
0/
1,
b1011 $
b1011 (
b1011 &
#28
0"
02
1=
0.
07
0<
1/
03
04
b0 *
08
b1101 !
b1101 )
19
0,
01
16
b1100 $
b1100 (
b1100 &
#29
14
12
b10 *
1.
b1110 !
b1110 )
0/
1,
b1101 $
b1101 (
b1101 &
#30
0"
1=
0<
08
02
19
0.
07
1/
b0 *
03
b1111 !
b1111 )
14
0,
11
b1110 $
b1110 (
b1110 &
#31
1"
0=
1<
18
09
17
13
04
12
b1110 *
1.
b0 !
b0 )
0/
1,
b1111 $
b1111 (
b1111 &
#32
07
03
14
02
0<
0.
b0 *
08
09
0"
b10 !
b10 )
0=
0,
01
06
0;
0+
10
b0 $
b0 (
b10 #
b10 '
b10 %
b0 &
#33
b11 !
b11 )
1/
1,
b1 $
b1 (
b1 &
#34
19
17
b100 *
13
0/
b100 !
b100 )
04
0,
11
b10 $
b10 (
b10 &
#35
b101 !
b101 )
1/
1,
b11 $
b11 (
b11 &
#36
07
0=
03
0<
0/
14
b0 *
08
b110 !
b110 )
19
0,
01
16
b100 $
b100 (
b100 &
#37
b111 !
b111 )
1/
1,
b101 $
b101 (
b101 &
#38
1=
1<
18
09
17
b1100 *
13
0/
b1000 !
b1000 )
04
0,
11
b110 $
b110 (
b110 &
#39
b1001 !
b1001 )
1/
1,
b111 $
b111 (
b111 &
#40
07
03
0<
0/
14
b0 *
08
09
0"
b1010 !
b1010 )
1=
0,
01
06
1;
b1000 $
b1000 (
b1000 &
#41
b1011 !
b1011 )
1/
1,
b1001 $
b1001 (
b1001 &
#42
19
17
b100 *
13
0/
b1100 !
b1100 )
04
0,
11
b1010 $
b1010 (
b1010 &
#43
b1101 !
b1101 )
1/
1,
b1011 $
b1011 (
b1011 &
#44
0"
07
1=
03
0<
0/
14
b0 *
08
b1110 !
b1110 )
19
0,
01
16
b1100 $
b1100 (
b1100 &
#45
b1111 !
b1111 )
1/
1,
b1101 $
b1101 (
b1101 &
#46
1"
0=
1<
18
09
17
b1100 *
13
0/
b0 !
b0 )
04
0,
11
b1110 $
b1110 (
b1110 &
#47
b1 !
b1 )
1/
1,
b1111 $
b1111 (
b1111 &
#48
07
03
0<
14
b0 *
08
09
0"
b11 !
b11 )
0=
0,
01
06
0;
1+
b0 $
b0 (
b11 #
b11 '
b11 %
b0 &
#49
19
17
13
04
12
b110 *
1.
b100 !
b100 )
0/
1,
b1 $
b1 (
b1 &
#50
02
b100 *
0.
1/
b101 !
b101 )
04
0,
11
b10 $
b10 (
b10 &
#51
14
12
b110 *
1.
b110 !
b110 )
0/
1,
b11 $
b11 (
b11 &
#52
07
03
02
0=
0.
0<
1/
14
b0 *
08
b111 !
b111 )
19
0,
01
16
b100 $
b100 (
b100 &
#53
1=
1<
18
09
17
13
04
12
b1110 *
1.
b1000 !
b1000 )
0/
1,
b101 $
b101 (
b101 &
#54
02
b1100 *
0.
1/
b1001 !
b1001 )
04
0,
11
b110 $
b110 (
b110 &
#55
14
12
b1110 *
1.
b1010 !
b1010 )
0/
1,
b111 $
b111 (
b111 &
#56
07
03
02
0.
0<
1/
14
b0 *
08
09
0"
b1011 !
b1011 )
1=
0,
01
06
1;
b1000 $
b1000 (
b1000 &
#57
19
17
13
04
12
b110 *
1.
b1100 !
b1100 )
0/
1,
b1001 $
b1001 (
b1001 &
#58
02
b100 *
0.
1/
b1101 !
b1101 )
04
0,
11
b1010 $
b1010 (
b1010 &
#59
14
12
b110 *
1.
b1110 !
b1110 )
0/
1,
b1011 $
b1011 (
b1011 &
#60
07
03
0"
02
1=
0.
0<
1/
14
b0 *
08
b1111 !
b1111 )
19
0,
01
16
b1100 $
b1100 (
b1100 &
#61
1"
0=
1<
18
09
17
13
04
12
b1110 *
1.
b0 !
b0 )
0/
1,
b1101 $
b1101 (
b1101 &
#62
02
b1100 *
0.
1/
b1 !
b1 )
04
0,
11
b1110 $
b1110 (
b1110 &
#63
14
12
b1110 *
1.
b10 !
b10 )
0/
1,
b1111 $
b1111 (
b1111 &
#64
0<
08
04
19
02
07
0.
b0 *
03
0"
b100 !
b100 )
0=
0,
01
06
0;
0+
00
15
b0 $
b0 (
b100 #
b100 '
b100 %
b0 &
#65
b101 !
b101 )
1/
1,
b1 $
b1 (
b1 &
#66
0/
b110 !
b110 )
14
0,
11
b10 $
b10 (
b10 &
#67
b111 !
b111 )
1/
1,
b11 $
b11 (
b11 &
#68
1=
1<
b1000 *
18
0/
04
b1000 !
b1000 )
09
0,
01
16
b100 $
b100 (
b100 &
#69
b1001 !
b1001 )
1/
1,
b101 $
b101 (
b101 &
#70
0/
b1010 !
b1010 )
14
0,
11
b110 $
b110 (
b110 &
#71
b1011 !
b1011 )
1/
1,
b111 $
b111 (
b111 &
#72
0<
b0 *
08
0/
04
19
0"
b1100 !
b1100 )
1=
0,
01
06
1;
b1000 $
b1000 (
b1000 &
#73
b1101 !
b1101 )
1/
1,
b1001 $
b1001 (
b1001 &
#74
0/
b1110 !
b1110 )
14
0,
11
b1010 $
b1010 (
b1010 &
#75
b1111 !
b1111 )
1/
1,
b1011 $
b1011 (
b1011 &
#76
1"
0=
1<
b1000 *
18
0/
04
b0 !
b0 )
09
0,
01
16
b1100 $
b1100 (
b1100 &
#77
b1 !
b1 )
1/
1,
b1101 $
b1101 (
b1101 &
#78
0/
b10 !
b10 )
14
0,
11
b1110 $
b1110 (
b1110 &
#79
b11 !
b11 )
1/
1,
b1111 $
b1111 (
b1111 &
#80
0<
b0 *
08
04
19
0"
b101 !
b101 )
0=
0,
01
06
0;
1+
b0 $
b0 (
b101 #
b101 '
b101 %
b0 &
#81
14
12
b10 *
1.
b110 !
b110 )
0/
1,
b1 $
b1 (
b1 &
#82
0=
0<
08
02
19
0.
07
1/
b0 *
03
b111 !
b111 )
14
0,
11
b10 $
b10 (
b10 &
#83
1=
1<
18
09
17
13
04
12
b1110 *
1.
b1000 !
b1000 )
0/
1,
b11 $
b11 (
b11 &
#84
02
0.
07
1/
b1000 *
03
04
b1001 !
b1001 )
09
0,
01
16
b100 $
b100 (
b100 &
#85
14
12
b1010 *
1.
b1010 !
b1010 )
0/
1,
b101 $
b101 (
b101 &
#86
02
09
0.
07
1/
b1000 *
03
b1011 !
b1011 )
14
0,
11
b110 $
b110 (
b110 &
#87
19
17
13
04
12
b1110 *
1.
b1100 !
b1100 )
0/
1,
b111 $
b111 (
b111 &
#88
0<
08
02
0.
07
1/
b0 *
03
04
19
0"
b1101 !
b1101 )
1=
0,
01
06
1;
b1000 $
b1000 (
b1000 &
#89
14
12
b10 *
1.
b1110 !
b1110 )
0/
1,
b1001 $
b1001 (
b1001 &
#90
0"
1=
0<
08
02
19
0.
07
1/
b0 *
03
b1111 !
b1111 )
14
0,
11
b1010 $
b1010 (
b1010 &
#91
1"
0=
1<
18
09
17
13
04
12
b1110 *
1.
b0 !
b0 )
0/
1,
b1011 $
b1011 (
b1011 &
#92
02
0.
07
1/
b1000 *
03
04
b1 !
b1 )
09
0,
01
16
b1100 $
b1100 (
b1100 &
#93
14
12
b1010 *
1.
b10 !
b10 )
0/
1,
b1101 $
b1101 (
b1101 &
#94
02
09
0.
07
1/
b1000 *
03
b11 !
b11 )
14
0,
11
b1110 $
b1110 (
b1110 &
#95
19
17
13
04
12
b1110 *
1.
b100 !
b100 )
0/
1,
b1111 $
b1111 (
b1111 &
#96
0<
08
07
03
14
02
b0 *
0.
19
0"
b110 !
b110 )
0=
0,
01
06
0;
0+
10
b0 $
b0 (
b110 #
b110 '
b110 %
b0 &
#97
b111 !
b111 )
1/
1,
b1 $
b1 (
b1 &
#98
1=
1<
18
09
17
b1100 *
13
0/
b1000 !
b1000 )
04
0,
11
b10 $
b10 (
b10 &
#99
b1001 !
b1001 )
1/
1,
b11 $
b11 (
b11 &
#100
07
b1000 *
03
0/
14
b1010 !
b1010 )
09
0,
01
16
b100 $
b100 (
b100 &
#101
b1011 !
b1011 )
1/
1,
b101 $
b101 (
b101 &
#102
19
17
b1100 *
13
0/
b1100 !
b1100 )
04
0,
11
b110 $
b110 (
b110 &
#103
b1101 !
b1101 )
1/
1,
b111 $
b111 (
b111 &
#104
0<
08
07
b0 *
03
0/
14
19
0"
b1110 !
b1110 )
1=
0,
01
06
1;
b1000 $
b1000 (
b1000 &
#105
b1111 !
b1111 )
1/
1,
b1001 $
b1001 (
b1001 &
#106
1"
0=
1<
18
09
17
b1100 *
13
0/
b0 !
b0 )
04
0,
11
b1010 $
b1010 (
b1010 &
#107
b1 !
b1 )
1/
1,
b1011 $
b1011 (
b1011 &
#108
07
b1000 *
03
0/
14
b10 !
b10 )
09
0,
01
16
b1100 $
b1100 (
b1100 &
#109
b11 !
b11 )
1/
1,
b1101 $
b1101 (
b1101 &
#110
19
17
b1100 *
13
0/
b100 !
b100 )
04
0,
11
b1110 $
b1110 (
b1110 &
#111
b101 !
b101 )
1/
1,
b1111 $
b1111 (
b1111 &
#112
0<
08
07
b0 *
03
14
19
0"
b111 !
b111 )
0=
0,
01
06
0;
1+
b0 $
b0 (
b111 #
b111 '
b111 %
b0 &
#113
1=
1<
18
09
17
13
04
12
b1110 *
1.
b1000 !
b1000 )
0/
1,
b1 $
b1 (
b1 &
#114
02
b1100 *
0.
1/
b1001 !
b1001 )
04
0,
11
b10 $
b10 (
b10 &
#115
14
12
b1110 *
1.
b1010 !
b1010 )
0/
1,
b11 $
b11 (
b11 &
#116
07
03
02
b1000 *
0.
1/
14
b1011 !
b1011 )
09
0,
01
16
b100 $
b100 (
b100 &
#117
19
17
13
04
12
b1110 *
1.
b1100 !
b1100 )
0/
1,
b101 $
b101 (
b101 &
#118
02
b1100 *
0.
1/
b1101 !
b1101 )
04
0,
11
b110 $
b110 (
b110 &
#119
14
12
b1110 *
1.
b1110 !
b1110 )
0/
1,
b111 $
b111 (
b111 &
#120
0<
08
07
03
02
b0 *
0.
1/
14
19
0"
b1111 !
b1111 )
1=
0,
01
06
1;
b1000 $
b1000 (
b1000 &
#121
1"
0=
1<
18
09
17
13
04
12
b1110 *
1.
b0 !
b0 )
0/
1,
b1001 $
b1001 (
b1001 &
#122
02
b1100 *
0.
1/
b1 !
b1 )
04
0,
11
b1010 $
b1010 (
b1010 &
#123
14
12
b1110 *
1.
b10 !
b10 )
0/
1,
b1011 $
b1011 (
b1011 &
#124
07
03
02
b1000 *
0.
1/
14
b11 !
b11 )
09
0,
01
16
b1100 $
b1100 (
b1100 &
#125
19
17
13
04
12
b1110 *
1.
b100 !
b100 )
0/
1,
b1101 $
b1101 (
b1101 &
#126
02
b1100 *
0.
1/
b101 !
b101 )
04
0,
11
b1110 $
b1110 (
b1110 &
#127
14
12
b1110 *
1.
b110 !
b110 )
0/
1,
b1111 $
b1111 (
b1111 &
#128
0"
04
09
b1000 !
b1000 )
1=
02
07
0<
0.
03
b0 *
08
0,
01
06
0;
0+
00
05
1:
b0 $
b0 (
b1000 #
b1000 '
b1000 %
b0 &
#129
b1001 !
b1001 )
1/
1,
b1 $
b1 (
b1 &
#130
0/
b1010 !
b1010 )
14
0,
11
b10 $
b10 (
b10 &
#131
b1011 !
b1011 )
1/
1,
b11 $
b11 (
b11 &
#132
0/
04
b1100 !
b1100 )
19
0,
01
16
b100 $
b100 (
b100 &
#133
b1101 !
b1101 )
1/
1,
b101 $
b101 (
b101 &
#134
0/
b1110 !
b1110 )
14
0,
11
b110 $
b110 (
b110 &
#135
b1111 !
b1111 )
1/
1,
b111 $
b111 (
b111 &
#136
1"
0/
04
09
b0 !
b0 )
0=
0,
01
06
1;
b1000 $
b1000 (
b1000 &
#137
b1 !
b1 )
1/
1,
b1001 $
b1001 (
b1001 &
#138
0/
b10 !
b10 )
14
0,
11
b1010 $
b1010 (
b1010 &
#139
b11 !
b11 )
1/
1,
b1011 $
b1011 (
b1011 &
#140
0/
04
b100 !
b100 )
19
0,
01
16
b1100 $
b1100 (
b1100 &
#141
b101 !
b101 )
1/
1,
b1101 $
b1101 (
b1101 &
#142
0/
b110 !
b110 )
14
0,
11
b1110 $
b1110 (
b1110 &
#143
b111 !
b111 )
1/
1,
b1111 $
b1111 (
b1111 &
#144
0"
04
09
b1001 !
b1001 )
1=
0,
01
06
0;
1+
b0 $
b0 (
b1001 #
b1001 '
b1001 %
b0 &
#145
14
12
b10 *
1.
b1010 !
b1010 )
0/
1,
b1 $
b1 (
b1 &
#146
02
09
0.
07
1/
b0 *
03
b1011 !
b1011 )
14
0,
11
b10 $
b10 (
b10 &
#147
19
17
13
04
12
b110 *
1.
b1100 !
b1100 )
0/
1,
b11 $
b11 (
b11 &
#148
0"
02
1=
0.
07
0<
1/
03
04
b0 *
08
b1101 !
b1101 )
19
0,
01
16
b100 $
b100 (
b100 &
#149
14
12
b10 *
1.
b1110 !
b1110 )
0/
1,
b101 $
b101 (
b101 &
#150
0"
1=
0<
08
02
19
0.
07
1/
b0 *
03
b1111 !
b1111 )
14
0,
11
b110 $
b110 (
b110 &
#151
1"
0=
1<
18
09
17
13
04
12
b1110 *
1.
b0 !
b0 )
0/
1,
b111 $
b111 (
b111 &
#152
02
0.
07
0<
1/
03
04
b0 *
08
09
b1 !
b1 )
0=
0,
01
06
1;
b1000 $
b1000 (
b1000 &
#153
14
12
b10 *
1.
b10 !
b10 )
0/
1,
b1001 $
b1001 (
b1001 &
#154
02
09
0.
07
1/
b0 *
03
b11 !
b11 )
14
0,
11
b1010 $
b1010 (
b1010 &
#155
19
17
13
04
12
b110 *
1.
b100 !
b100 )
0/
1,
b1011 $
b1011 (
b1011 &
#156
02
0=
0.
07
0<
1/
03
04
b0 *
08
b101 !
b101 )
19
0,
01
16
b1100 $
b1100 (
b1100 &
#157
14
12
b10 *
1.
b110 !
b110 )
0/
1,
b1101 $
b1101 (
b1101 &
#158
0=
0<
08
02
19
0.
07
1/
b0 *
03
b111 !
b111 )
14
0,
11
b1110 $
b1110 (
b1110 &
#159
1=
1<
18
09
17
13
04
12
b1110 *
1.
b1000 !
b1000 )
0/
1,
b1111 $
b1111 (
b1111 &
#160
07
03
0"
14
02
0<
0.
b0 *
08
09
b1010 !
b1010 )
1=
0,
01
06
0;
0+
10
b0 $
b0 (
b1010 #
b1010 '
b1010 %
b0 &
#161
b1011 !
b1011 )
1/
1,
b1 $
b1 (
b1 &
#162
19
17
b100 *
13
0/
b1100 !
b1100 )
04
0,
11
b10 $
b10 (
b10 &
#163
b1101 !
b1101 )
1/
1,
b11 $
b11 (
b11 &
#164
0"
07
1=
03
0<
0/
14
b0 *
08
b1110 !
b1110 )
19
0,
01
16
b100 $
b100 (
b100 &
#165
b1111 !
b1111 )
1/
1,
b101 $
b101 (
b101 &
#166
1"
0=
1<
18
09
17
b1100 *
13
0/
b0 !
b0 )
04
0,
11
b110 $
b110 (
b110 &
#167
b1 !
b1 )
1/
1,
b111 $
b111 (
b111 &
#168
07
03
0<
0/
14
b0 *
08
09
b10 !
b10 )
0=
0,
01
06
1;
b1000 $
b1000 (
b1000 &
#169
b11 !
b11 )
1/
1,
b1001 $
b1001 (
b1001 &
#170
19
17
b100 *
13
0/
b100 !
b100 )
04
0,
11
b1010 $
b1010 (
b1010 &
#171
b101 !
b101 )
1/
1,
b1011 $
b1011 (
b1011 &
#172
07
0=
03
0<
0/
14
b0 *
08
b110 !
b110 )
19
0,
01
16
b1100 $
b1100 (
b1100 &
#173
b111 !
b111 )
1/
1,
b1101 $
b1101 (
b1101 &
#174
1=
1<
18
09
17
b1100 *
13
0/
b1000 !
b1000 )
04
0,
11
b1110 $
b1110 (
b1110 &
#175
b1001 !
b1001 )
1/
1,
b1111 $
b1111 (
b1111 &
#176
0"
07
03
0<
14
b0 *
08
09
b1011 !
b1011 )
1=
0,
01
06
0;
1+
b0 $
b0 (
b1011 #
b1011 '
b1011 %
b0 &
#177
19
17
13
04
12
b110 *
1.
b1100 !
b1100 )
0/
1,
b1 $
b1 (
b1 &
#178
02
b100 *
0.
1/
b1101 !
b1101 )
04
0,
11
b10 $
b10 (
b10 &
#179
14
12
b110 *
1.
b1110 !
b1110 )
0/
1,
b11 $
b11 (
b11 &
#180
07
03
0"
02
1=
0.
0<
1/
14
b0 *
08
b1111 !
b1111 )
19
0,
01
16
b100 $
b100 (
b100 &
#181
1"
0=
1<
18
09
17
13
04
12
b1110 *
1.
b0 !
b0 )
0/
1,
b101 $
b101 (
b101 &
#182
02
b1100 *
0.
1/
b1 !
b1 )
04
0,
11
b110 $
b110 (
b110 &
#183
14
12
b1110 *
1.
b10 !
b10 )
0/
1,
b111 $
b111 (
b111 &
#184
07
03
02
0.
0<
1/
14
b0 *
08
09
b11 !
b11 )
0=
0,
01
06
1;
b1000 $
b1000 (
b1000 &
#185
19
17
13
04
12
b110 *
1.
b100 !
b100 )
0/
1,
b1001 $
b1001 (
b1001 &
#186
02
b100 *
0.
1/
b101 !
b101 )
04
0,
11
b1010 $
b1010 (
b1010 &
#187
14
12
b110 *
1.
b110 !
b110 )
0/
1,
b1011 $
b1011 (
b1011 &
#188
07
03
02
0=
0.
0<
1/
14
b0 *
08
b111 !
b111 )
19
0,
01
16
b1100 $
b1100 (
b1100 &
#189
1=
1<
18
09
17
13
04
12
b1110 *
1.
b1000 !
b1000 )
0/
1,
b1101 $
b1101 (
b1101 &
#190
02
b1100 *
0.
1/
b1001 !
b1001 )
04
0,
11
b1110 $
b1110 (
b1110 &
#191
14
12
b1110 *
1.
b1010 !
b1010 )
0/
1,
b1111 $
b1111 (
b1111 &
#192
0"
0<
08
04
19
02
07
0.
b0 *
03
b1100 !
b1100 )
1=
0,
01
06
0;
0+
00
15
b0 $
b0 (
b1100 #
b1100 '
b1100 %
b0 &
#193
b1101 !
b1101 )
1/
1,
b1 $
b1 (
b1 &
#194
0/
b1110 !
b1110 )
14
0,
11
b10 $
b10 (
b10 &
#195
b1111 !
b1111 )
1/
1,
b11 $
b11 (
b11 &
#196
1"
0=
1<
b1000 *
18
0/
04
b0 !
b0 )
09
0,
01
16
b100 $
b100 (
b100 &
#197
b1 !
b1 )
1/
1,
b101 $
b101 (
b101 &
#198
0/
b10 !
b10 )
14
0,
11
b110 $
b110 (
b110 &
#199
b11 !
b11 )
1/
1,
b111 $
b111 (
b111 &
#200
0<
b0 *
08
0/
04
19
b100 !
b100 )
0=
0,
01
06
1;
b1000 $
b1000 (
b1000 &
#201
b101 !
b101 )
1/
1,
b1001 $
b1001 (
b1001 &
#202
0/
b110 !
b110 )
14
0,
11
b1010 $
b1010 (
b1010 &
#203
b111 !
b111 )
1/
1,
b1011 $
b1011 (
b1011 &
#204
1=
1<
b1000 *
18
0/
04
b1000 !
b1000 )
09
0,
01
16
b1100 $
b1100 (
b1100 &
#205
b1001 !
b1001 )
1/
1,
b1101 $
b1101 (
b1101 &
#206
0/
b1010 !
b1010 )
14
0,
11
b1110 $
b1110 (
b1110 &
#207
b1011 !
b1011 )
1/
1,
b1111 $
b1111 (
b1111 &
#208
0"
0<
b0 *
08
04
19
b1101 !
b1101 )
1=
0,
01
06
0;
1+
b0 $
b0 (
b1101 #
b1101 '
b1101 %
b0 &
#209
14
12
b10 *
1.
b1110 !
b1110 )
0/
1,
b1 $
b1 (
b1 &
#210
0"
1=
0<
08
02
19
0.
07
1/
b0 *
03
b1111 !
b1111 )
14
0,
11
b10 $
b10 (
b10 &
#211
1"
0=
1<
18
09
17
13
04
12
b1110 *
1.
b0 !
b0 )
0/
1,
b11 $
b11 (
b11 &
#212
02
0.
07
1/
b1000 *
03
04
b1 !
b1 )
09
0,
01
16
b100 $
b100 (
b100 &
#213
14
12
b1010 *
1.
b10 !
b10 )
0/
1,
b101 $
b101 (
b101 &
#214
02
09
0.
07
1/
b1000 *
03
b11 !
b11 )
14
0,
11
b110 $
b110 (
b110 &
#215
19
17
13
04
12
b1110 *
1.
b100 !
b100 )
0/
1,
b111 $
b111 (
b111 &
#216
0<
08
02
0.
07
1/
b0 *
03
04
19
b101 !
b101 )
0=
0,
01
06
1;
b1000 $
b1000 (
b1000 &
#217
14
12
b10 *
1.
b110 !
b110 )
0/
1,
b1001 $
b1001 (
b1001 &
#218
0=
0<
08
02
19
0.
07
1/
b0 *
03
b111 !
b111 )
14
0,
11
b1010 $
b1010 (
b1010 &
#219
1=
1<
18
09
17
13
04
12
b1110 *
1.
b1000 !
b1000 )
0/
1,
b1011 $
b1011 (
b1011 &
#220
02
0.
07
1/
b1000 *
03
04
b1001 !
b1001 )
09
0,
01
16
b1100 $
b1100 (
b1100 &
#221
14
12
b1010 *
1.
b1010 !
b1010 )
0/
1,
b1101 $
b1101 (
b1101 &
#222
02
09
0.
07
1/
b1000 *
03
b1011 !
b1011 )
14
0,
11
b1110 $
b1110 (
b1110 &
#223
19
17
13
04
12
b1110 *
1.
b1100 !
b1100 )
0/
1,
b1111 $
b1111 (
b1111 &
#224
0"
0<
08
07
03
14
02
b0 *
0.
19
b1110 !
b1110 )
1=
0,
01
06
0;
0+
10
b0 $
b0 (
b1110 #
b1110 '
b1110 %
b0 &
#225
b1111 !
b1111 )
1/
1,
b1 $
b1 (
b1 &
#226
1"
0=
1<
18
09
17
b1100 *
13
0/
b0 !
b0 )
04
0,
11
b10 $
b10 (
b10 &
#227
b1 !
b1 )
1/
1,
b11 $
b11 (
b11 &
#228
07
b1000 *
03
0/
14
b10 !
b10 )
09
0,
01
16
b100 $
b100 (
b100 &
#229
b11 !
b11 )
1/
1,
b101 $
b101 (
b101 &
#230
19
17
b1100 *
13
0/
b100 !
b100 )
04
0,
11
b110 $
b110 (
b110 &
#231
b101 !
b101 )
1/
1,
b111 $
b111 (
b111 &
#232
0<
08
07
b0 *
03
0/
14
19
b110 !
b110 )
0=
0,
01
06
1;
b1000 $
b1000 (
b1000 &
#233
b111 !
b111 )
1/
1,
b1001 $
b1001 (
b1001 &
#234
1=
1<
18
09
17
b1100 *
13
0/
b1000 !
b1000 )
04
0,
11
b1010 $
b1010 (
b1010 &
#235
b1001 !
b1001 )
1/
1,
b1011 $
b1011 (
b1011 &
#236
07
b1000 *
03
0/
14
b1010 !
b1010 )
09
0,
01
16
b1100 $
b1100 (
b1100 &
#237
b1011 !
b1011 )
1/
1,
b1101 $
b1101 (
b1101 &
#238
19
17
b1100 *
13
0/
b1100 !
b1100 )
04
0,
11
b1110 $
b1110 (
b1110 &
#239
b1101 !
b1101 )
1/
1,
b1111 $
b1111 (
b1111 &
#240
0"
0<
08
07
b0 *
03
14
19
b1111 !
b1111 )
1=
0,
01
06
0;
1+
b0 $
b0 (
b1111 #
b1111 '
b1111 %
b0 &
#241
1"
0=
1<
18
09
17
13
04
12
b1110 *
1.
b0 !
b0 )
0/
1,
b1 $
b1 (
b1 &
#242
02
b1100 *
0.
1/
b1 !
b1 )
04
0,
11
b10 $
b10 (
b10 &
#243
14
12
b1110 *
1.
b10 !
b10 )
0/
1,
b11 $
b11 (
b11 &
#244
07
03
02
b1000 *
0.
1/
14
b11 !
b11 )
09
0,
01
16
b100 $
b100 (
b100 &
#245
19
17
13
04
12
b1110 *
1.
b100 !
b100 )
0/
1,
b101 $
b101 (
b101 &
#246
02
b1100 *
0.
1/
b101 !
b101 )
04
0,
11
b110 $
b110 (
b110 &
#247
14
12
b1110 *
1.
b110 !
b110 )
0/
1,
b111 $
b111 (
b111 &
#248
0<
08
07
03
02
b0 *
0.
1/
14
19
b111 !
b111 )
0=
0,
01
06
1;
b1000 $
b1000 (
b1000 &
#249
1=
1<
18
09
17
13
04
12
b1110 *
1.
b1000 !
b1000 )
0/
1,
b1001 $
b1001 (
b1001 &
#250
02
b1100 *
0.
1/
b1001 !
b1001 )
04
0,
11
b1010 $
b1010 (
b1010 &
#251
14
12
b1110 *
1.
b1010 !
b1010 )
0/
1,
b1011 $
b1011 (
b1011 &
#252
07
03
02
b1000 *
0.
1/
14
b1011 !
b1011 )
09
0,
01
16
b1100 $
b1100 (
b1100 &
#253
19
17
13
04
12
b1110 *
1.
b1100 !
b1100 )
0/
1,
b1101 $
b1101 (
b1101 &
#254
02
b1100 *
0.
1/
b1101 !
b1101 )
04
0,
11
b1110 $
b1110 (
b1110 &
#255
14
12
b1110 *
1.
b1110 !
b1110 )
0/
1,
b1111 $
b1111 (
b1111 &
